paz/__init__.py
paz/__main__.py
paz/breach.py
paz/cli.py
paz/strength.py
paz_cli-1.0.2.dist-info/licenses/LICENSE
paz_cli-1.0.2.dist-info/METADATA
paz_cli-1.0.2.dist-info/WHEEL
paz_cli-1.0.2.dist-info/entry_points.txt
paz_cli-1.0.2.dist-info/top_level.txt
paz_cli-1.0.2.dist-info/RECORD
