Metadata-Version: 2.4
Name: paz-cli
Version: 1.0.2
Summary: A CLI tool to analyze password strength and breach status
Home-page: https://github.com/MahdiMirshafiee/password-analyzer-cli
Author: Mahdi Mirshafiee
Classifier: Programming Language :: Python :: 3
Classifier: License :: OSI Approved :: MIT License
Requires-Python: >=3.10
License-File: LICENSE
Requires-Dist: click>=8.0
Requires-Dist: requests>=2.0
Requires-Dist: rich>=10.0
Requires-Dist: pyhibp>=1.0
Dynamic: author
Dynamic: classifier
Dynamic: description
Dynamic: description-content-type
Dynamic: home-page
Dynamic: license-file
Dynamic: requires-dist
Dynamic: requires-python
Dynamic: summary
